panel_splitjs/__init__.py
panel_splitjs/__version.py
panel_splitjs/_version.py
panel_splitjs/base.py
panel_splitjs/dist/panel-splitjs.bundle.js
panel_splitjs/dist/css/arrow_down.svg
panel_splitjs/dist/css/arrow_left.svg
panel_splitjs/dist/css/arrow_right.svg
panel_splitjs/dist/css/arrow_up.svg
panel_splitjs/dist/css/handle.svg
panel_splitjs/dist/css/handle_vertical.svg
panel_splitjs/dist/css/splitjs.css
panel_splitjs/models/multi_split.js
panel_splitjs/models/split.js
panel_splitjs-0.3.1.dist-info/METADATA
panel_splitjs-0.3.1.dist-info/WHEEL
panel_splitjs-0.3.1.dist-info/licenses/LICENSE.txt
panel_splitjs-0.3.1.dist-info/RECORD
